bluesky_queueserver_api/__init__.py
bluesky_queueserver_api/_defaults.py
bluesky_queueserver_api/_version.py
bluesky_queueserver_api/api_async.py
bluesky_queueserver_api/api_base.py
bluesky_queueserver_api/api_docstrings.py
bluesky_queueserver_api/api_threads.py
bluesky_queueserver_api/comm_async.py
bluesky_queueserver_api/comm_base.py
bluesky_queueserver_api/comm_threads.py
bluesky_queueserver_api/console_monitor.py
bluesky_queueserver_api/item.py
bluesky_queueserver_api/system_info_monitor.py
bluesky_queueserver_api/http/__init__.py
bluesky_queueserver_api/http/aio.py
bluesky_queueserver_api/tests/__init__.py
bluesky_queueserver_api/tests/common.py
bluesky_queueserver_api/tests/conftest.py
bluesky_queueserver_api/tests/test_api.py
bluesky_queueserver_api/tests/test_api_fs.py
bluesky_queueserver_api/tests/test_comm.py
bluesky_queueserver_api/tests/test_item_classes.py
bluesky_queueserver_api/tests/test_security.py
bluesky_queueserver_api/zmq/__init__.py
bluesky_queueserver_api/zmq/aio.py
bluesky_queueserver_api-0.0.13.dist-info/licenses/AUTHORS.rst
bluesky_queueserver_api-0.0.13.dist-info/licenses/LICENSE
bluesky_queueserver_api-0.0.13.dist-info/METADATA
bluesky_queueserver_api-0.0.13.dist-info/WHEEL
bluesky_queueserver_api-0.0.13.dist-info/top_level.txt
bluesky_queueserver_api-0.0.13.dist-info/RECORD
