Metadata-Version: 2.4
Name: bluesky-queueserver-api
Version: 0.0.13
Summary: Python API for Bluesky Queue Server
Home-page: https://github.com/bluesky/bluesky-queueserver-api
Author: Brookhaven National Laboratory
Author-email: 
License: BSD (3-clause)
Classifier: Development Status :: 2 - Pre-Alpha
Classifier: Natural Language :: English
Classifier: Programming Language :: Python :: 3
Requires-Python: >=3.7
License-File: LICENSE
License-File: AUTHORS.rst
Requires-Dist: bluesky-queueserver
Requires-Dist: websockets
Requires-Dist: httpx
Dynamic: author
Dynamic: classifier
Dynamic: description
Dynamic: home-page
Dynamic: license
Dynamic: license-file
Dynamic: requires-dist
Dynamic: requires-python
Dynamic: summary
